[
  {
    "_id": { "$oid": "642a1bc123456789abcdef41" },
    "blogPost": { "$oid": "642a1bc123456789abcdef21" },
    "name": "Alex Turner",
    "email": "alex.turner@example.com",
    "content": "Great article! The explanation of Server Components vs SSR was particularly helpful. When can we expect Server Components to be stable outside of Next.js?",
    "isApproved": true,
    "isAuthor": false,
    "parentComment": null,
    "likes": 12,
    "reports": 0,
    "userIp": "192.168.1.100",
    "userAgent": "Mozilla/5.0 (Macintosh; Intel Mac OS X 10_15_7)",
    "createdAt": { "$date": "2024-01-15T11:30:00.000Z" },
    "updatedAt": { "$date": "2024-01-15T11:30:00.000Z" }
  },
  {
    "_id": { "$oid": "642a1bc123456789abcdef42" },
    "blogPost": { "$oid": "642a1bc123456789abcdef21" },
    "user": null,
    "name": "Sarah Johnson",
    "email": "sarah.johnson@example.com",
    "content": "Thanks for the question, Alex! The React team has mentioned that Server Components should be framework-agnostic by mid-2024. For now, Next.js 13+ is the most stable implementation.",
    "isApproved": true,
    "isAuthor": true,
    "parentComment": { "$oid": "642a1bc123456789abcdef41" },
    "likes": 5,
    "reports": 0,
    "createdAt": { "$date": "2024-01-15T12:15:00.000Z" },
    "updatedAt": { "$date": "2024-01-15T12:15:00.000Z" }
  },
  {
    "_id": { "$oid": "642a1bc123456789abcdef43" },
    "blogPost": { "$oid": "642a1bc123456789abcdef22" },
    "name": "Jordan Lee",
    "email": "jordan.lee@example.com",
    "content": "The error-first pattern with async functions is a game changer! Been using it in production and it's made error handling much cleaner.",
    "isApproved": true,
    "isAuthor": false,
    "parentComment": null,
    "likes": 8,
    "reports": 0,
    "userIp": "10.0.0.50",
    "userAgent": "Mozilla/5.0 (Windows NT 10.0; Win64; x64)",
    "createdAt": { "$date": "2024-01-10T15:45:00.000Z" },
    "updatedAt": { "$date": "2024-01-10T15:45:00.000Z" }
  },
  {
    "_id": { "$oid": "642a1bc123456789abcdef44" },
    "blogPost": { "$oid": "642a1bc123456789abcdef22" },
    "name": "Taylor Reed",
    "email": "taylor.reed@example.com",
    "content": "I'm confused about the parallel execution example. Wouldn't Promise.all reject immediately if any promise rejects? How do you handle partial failures?",
    "isApproved": true,
    "isAuthor": false,
    "parentComment": null,
    "likes": 3,
    "reports": 0,
    "createdAt": { "$date": "2024-01-11T09:20:00.000Z" },
    "updatedAt": { "$date": "2024-01-11T09:20:00.000Z" }
  },
  {
    "_id": { "$oid": "642a1bc123456789abcdef45" },
    "blogPost": { "$oid": "642a1bc123456789abcdef22" },
    "name": "Michael Chen",
    "email": "michael.chen@example.com",
    "content": "Good question, Taylor! You're right about Promise.all. For partial failures, you can use Promise.allSettled() or wrap each promise in error handling. I'll add a section about this in a future update.",
    "isApproved": true,
    "isAuthor": true,
    "parentComment": { "$oid": "642a1bc123456789abcdef44" },
    "likes": 7,
    "reports": 0,
    "createdAt": { "$date": "2024-01-11T10:30:00.000Z" },
    "updatedAt": { "$date": "2024-01-11T10:30:00.000Z" }
  },
  {
    "_id": { "$oid": "642a1bc123456789abcdef46" },
    "blogPost": { "$oid": "642a1bc123456789abcdef24" },
    "name": "Casey Smith",
    "email": "casey.smith@example.com",
    "content": "This is exactly what I needed! Been struggling with complex aggregations. The $lookup examples were particularly helpful. More MongoDB content please!",
    "isApproved": true,
    "isAuthor": false,
    "parentComment": null,
    "likes": 4,
    "reports": 0,
    "createdAt": { "$date": "2024-01-03T17:30:00.000Z" },
    "updatedAt": { "$date": "2024-01-03T17:30:00.000Z" }
  },
  {
    "_id": { "$oid": "642a1bc123456789abcdef47" },
    "blogPost": { "$oid": "642a1bc123456789abcdef23" },
    "name": "Spam Bot",
    "email": "spam@example.com",
    "content": "Buy cheap followers here! Visit my website for fake engagement!",
    "isApproved": false,
    "isAuthor": false,
    "parentComment": null,
    "likes": 0,
    "reports": 3,
    "userIp": "103.106.238.55",
    "userAgent": "Python/3.9",
    "createdAt": { "$date": "2024-01-06T03:15:00.000Z" },
    "updatedAt": { "$date": "2024-01-06T03:15:00.000Z" }
  }
]
